trellis_process/__init__.py
trellis_process/domain.py
trellis_process/exceptions.py
trellis_process/py.typed
trellis_process/repositories/__init__.py
trellis_process/repositories/base.py
trellis_process/repositories/dynamodb.py
trellis_process/repositories/inmemory.py
trellis_process/repositories/tracker_base.py
trellis_process/repositories/tracker_dynamodb.py
trellis_process/repositories/tracker_inmemory.py
trellis_process/service.py
trellis_process/timeout_service.py
trellis_process/tracker.py
trellis_process-0.4.1.dist-info/METADATA
trellis_process-0.4.1.dist-info/WHEEL
trellis_process-0.4.1.dist-info/RECORD
