Metadata-Version: 2.4
Name: trellis-process
Version: 0.4.1
Summary: A lightweight process tracker (Process / ProcessStep) for long-running, distributed workflows.
License: MIT
Keywords: workflow,saga,process-tracker,ddd,distributed-systems
Author: Anthony Morris
Author-email: morrisaa@v-is.com
Requires-Python: >=3.10,<4.0
Classifier: Development Status :: 3 - Alpha
Classifier: Intended Audience :: Developers
Classifier: License :: OSI Approved :: MIT License
Classifier: Programming Language :: Python
Classifier: Programming Language :: Python :: 3
Classifier: Programming Language :: Python :: 3.10
Classifier: Programming Language :: Python :: 3.11
Classifier: Programming Language :: Python :: 3.12
Classifier: Programming Language :: Python :: 3.13
Classifier: Programming Language :: Python :: 3.14
Classifier: Topic :: Software Development :: Libraries
Classifier: Topic :: Software Development :: Libraries :: Python Modules
Provides-Extra: dynamodb
Requires-Dist: boto3 (>=1.35.0,<2.0.0) ; extra == "dynamodb"
Project-URL: Homepage, https://github.com/Versailles-Information-Systems/trellis-process
Project-URL: Repository, https://github.com/Versailles-Information-Systems/trellis-process
